fw_gear_freesurferator/__init__.py
fw_gear_freesurferator/main.py
fw_gear_freesurferator/parser.py
fw_gear_freesurferator/segmentations.py
fw_gear_freesurferator/separateROIs.py
fw_gear_freesurferator/utils.py
fw_gear_freesurferator-0.2.1.dist-info/LICENSE
fw_gear_freesurferator-0.2.1.dist-info/METADATA
fw_gear_freesurferator-0.2.1.dist-info/WHEEL
fw_gear_freesurferator-0.2.1.dist-info/RECORD
