Metadata-Version: 2.1
Name: fw-gear-freesurferator
Version: 0.2.1
Summary: 
Home-page: https://gitlab.com/flywheel-io/scientific-solutions/gears/freesurferator
License: MIT
Keywords: Flywheel,Gears
Author: Flywheel
Author-email: support@flywheel.io
Requires-Python: >=3.9,<4.0
Classifier: License :: OSI Approved :: MIT License
Classifier: Programming Language :: Python :: 3
Classifier: Programming Language :: Python :: 3.9
Classifier: Programming Language :: Python :: 3.10
Classifier: Programming Language :: Python :: 3.11
Classifier: Programming Language :: Python :: 3.12
Classifier: Topic :: Scientific/Engineering
Requires-Dist: flywheel-gear-toolkit (==0.6.8)
Requires-Dist: flywheel-sdk (>=17.4.1,<18.0.0)
Requires-Dist: neuropythy (>=0.12.13,<0.13.0)
Requires-Dist: pandas (>=2.2.2,<3.0.0)
Requires-Dist: urllib3 (==1.26.18)
Project-URL: Repository, https://gitlab.com/flywheel-io/scientific-solutions/gears/freesurferator
